join_iterables
